docs/conf.py
docs/backends/generate_backend_class_hierarchy.py
docs/plugins/generate_plugin_class_hierarchy.py
dsi/_version.py
dsi/cli.py
dsi/core.py
dsi/dsi.py
dsi/backends/duckdb.py
dsi/backends/filesystem.py
dsi/backends/gufi.py
dsi/backends/hpss.py
dsi/backends/sqlalchemy.py
dsi/backends/sqlite.py
dsi/backends/tests/test_duckdb.py
dsi/backends/tests/test_gufi.py
dsi/backends/tests/test_hpss.py
dsi/backends/tests/test_sqlalchemy.py
dsi/backends/tests/test_sqlite.py
dsi/plugins/collection_reader.py
dsi/plugins/env.py
dsi/plugins/file_reader.py
dsi/plugins/file_writer.py
dsi/plugins/metadata.py
dsi/plugins/plugin.py
dsi/plugins/plugin_models.py
dsi/plugins/tests/test_collection_reader.py
dsi/plugins/tests/test_env.py
dsi/plugins/tests/test_file_reader.py
dsi/plugins/tests/test_file_writer.py
dsi/tests/test_core.py
dsi/tests/test_dsi.py
examples/datasync/datacopy.py
examples/datasync/datacopyhpss.py
examples/datasync/old.datasync.py
examples/developer/1.baseline.py
examples/developer/10.notebook.py
examples/developer/2.ingest.py
examples/developer/3.schema.py
examples/developer/4.visualize.py
examples/developer/5.process.py
examples/developer/6.find.py
examples/developer/7.query.py
examples/developer/8.overwrite.py
examples/developer/9.external_reader.py
examples/pennant/dsi_pennant.py
examples/pennant/dsi_pennant_dev.py
examples/pennant/parse_slurm_output.py
examples/test/coreterminal.py
examples/test/dsi_example.py
examples/test/text_file_reader.py
examples/user/1.baseline.py
examples/user/2.read.py
examples/user/3.visualize.py
examples/user/4.find.py
examples/user/5.update.py
examples/user/6.query.py
examples/user/7.schema.py
examples/user/8.write.py
examples/user/9.external_reader.py
examples/wildfire/wildfire.py
examples/wildfire/wildfire_dev.py
examples/wildfire/wildfire_pycinema.py
examples/wildfire/wildfire_terminal.py
dsi_workflow-1.1.3.dist-info/METADATA
dsi_workflow-1.1.3.dist-info/WHEEL
dsi_workflow-1.1.3.dist-info/entry_points.txt
dsi_workflow-1.1.3.dist-info/top_level.txt
dsi_workflow-1.1.3.dist-info/RECORD
